<!--
//============================================================================
// Name        : hf_tprime.xml
//============================================================================
-->

<!--
    Top-level configuration,  details for the single channel are in hf_tprime_channel.xml.
    This is the input file to the executable.

    Note: Config.dtd needs to be accessible.  It can be found in ROOT release area.  
    The file system path is relative to location of this XML file, not the executable.
-->

<!DOCTYPE Combination  SYSTEM './config/HistFactorySchema.dtd'>

<Combination OutputFilePrefix="./results/tprime" >

  <!--  <Input>hf_tprime_dilepton.xml</Input>-->
  <Input>hf_tprime_e.5.32.xml</Input> 
  <Input>hf_tprime_mu.5.32.xml</Input>

  <Measurement Name="tprimeCrossSection" Lumi="1.0" LumiRelErr="0.046" ExportOnly="True">

    <POI>xsec</POI>

    <ParamSetting Const="True">norm_ewk_mu norm_ewk_e</ParamSetting>
    
    <ConstraintTerm Type="Gaussian" RelativeUncertainty=".05">alpha_jes</ConstraintTerm>
    <ConstraintTerm Type="Gaussian" RelativeUncertainty=".05">alpha_btag_syst</ConstraintTerm>
    <ConstraintTerm Type="Gaussian" RelativeUncertainty=".114">alpha_norm_top_syst</ConstraintTerm>
    <ConstraintTerm Type="Gaussian" RelativeUncertainty=".50">alpha_norm_ewk_syst</ConstraintTerm>
    <ConstraintTerm Type="Gaussian" RelativeUncertainty=".03">alpha_lepton_eff_e</ConstraintTerm>
    <ConstraintTerm Type="Gaussian" RelativeUncertainty=".03">alpha_lepton_eff_mu</ConstraintTerm>

  </Measurement>
  
</Combination>
